marlinblocks/__init__.py
marlinblocks/acoustic_frame.py
marlinblocks/bot.py
marlinblocks/geo_frame.py
marlinblocks/marlin.py
marlinblocks/model_frame.py
marlinblocks/run_ais.py
marlinblocks/run_marlin_framework.py
marlinblocks/snapshot.py
marlinblocks/std_imports.py
marlinblocks/test.py
marlinblocks/utils.py
marlinblocks/xr.py
marlinblocks-0.0.7.dist-info/LICENSE
marlinblocks-0.0.7.dist-info/METADATA
marlinblocks-0.0.7.dist-info/WHEEL
marlinblocks-0.0.7.dist-info/top_level.txt
marlinblocks-0.0.7.dist-info/RECORD
